README.rst
setup.py
PyramidLogService.egg-info/PKG-INFO
PyramidLogService.egg-info/SOURCES.txt
PyramidLogService.egg-info/dependency_links.txt
PyramidLogService.egg-info/not-zip-safe
PyramidLogService.egg-info/requires.txt
PyramidLogService.egg-info/top_level.txt
logservice/__init__.py
logservice/base.py
logservice/log.py
logservice/handlers/__init__.py
logservice/handlers/sqlalchemy_handler.py
logservice/models/__init__.py
logservice/models/log.py
logservice/models/meta.py
logservice/scripts/__init__.py
logservice/scripts/initializedb.py