Metadata-Version: 1.1
Name: PyramidLogService
Version: 0.1
Summary: Pyramid LogService
Home-page: UNKNOWN
Author: Steven Locke
Author-email: steve.m.locke@gmail.com
License: UNKNOWN
Keywords: web services
Platform: UNKNOWN
Classifier: Programming Language :: Python
